{
  "schemaVersion": "1.0.0",
  "kind": "internal-text-package",
  "assets": [
    {
      "guid": "9a1c8019-2c7d-4168-a370-4ef4233a96aa",
      "kind": "material",
      "payload": {
        "kind": "material",
        "parent": 0,
        "paramValues": {
          "baseColor": [
            1,
            0.6,
            0,
            1
          ],
          "roughness": 0.1,
          "emissive": [
            1,
            0.5,
            0
          ],
          "emissiveIntensity": 6
        }
      },
      "refs": [
        "dd9e6e76-c926-43be-b575-bdd26661a939"
      ]
    }
  ]
}
